deltachat_cursed/__init__.py
deltachat_cursed/__main__.py
deltachat_cursed/_version.py
deltachat_cursed/application.py
deltachat_cursed/cards_widget.py
deltachat_cursed/chatlist.py
deltachat_cursed/cli.py
deltachat_cursed/composer.py
deltachat_cursed/container.py
deltachat_cursed/conversation.py
deltachat_cursed/eventcenter.py
deltachat_cursed/lazylistwaker.py
deltachat_cursed/logger.py
deltachat_cursed/main.py
deltachat_cursed/util.py
deltachat_cursed/welcome_widget.py
deltachat_cursed-0.10.1.dist-info/LICENSE
deltachat_cursed-0.10.1.dist-info/METADATA
deltachat_cursed-0.10.1.dist-info/WHEEL
deltachat_cursed-0.10.1.dist-info/entry_points.txt
deltachat_cursed-0.10.1.dist-info/top_level.txt
deltachat_cursed-0.10.1.dist-info/RECORD
