Metadata-Version: 2.2
Name: deltachat-cursed
Version: 0.10.1
Summary: Delta Chat client for the command line
Author-email: adbenitez <adb@merlinux.eu>
Project-URL: Homepage, https://github.com/adbenitez/deltachat-cursed
Project-URL: Issues, https://github.com/adbenitez/deltachat-cursed/issues
Keywords: deltachat,ncurses,tui
Classifier: Development Status :: 4 - Beta
Classifier: Intended Audience :: End Users/Desktop
Classifier: License :: OSI Approved :: GNU General Public License v3 (GPLv3)
Classifier: Operating System :: POSIX
Classifier: Programming Language :: Python :: 3
Requires-Python: >=3.8
License-File: LICENSE
Requires-Dist: arcanechat-tui
Provides-Extra: full
Requires-Dist: deltachat-rpc-server>=1.136.6; extra == "full"
Provides-Extra: dev
Requires-Dist: deltachat-rpc-server; extra == "dev"
Requires-Dist: black; extra == "dev"
Requires-Dist: mypy; extra == "dev"
Requires-Dist: isort; extra == "dev"
Requires-Dist: pylint; extra == "dev"
Requires-Dist: pylama; extra == "dev"
Requires-Dist: pytest; extra == "dev"
